CHANGES.rst
MANIFEST.in
README.rst
buildout.cfg
requirements-coverage.txt
requirements-tests.txt
setup.py
docs/LICENSE.GPL
docs/LICENSE.txt
docs/MIGRATION.txt
src/Products/__init__.py
src/Products.MeetingCPASLalouviere.egg-info/PKG-INFO
src/Products.MeetingCPASLalouviere.egg-info/SOURCES.txt
src/Products.MeetingCPASLalouviere.egg-info/dependency_links.txt
src/Products.MeetingCPASLalouviere.egg-info/namespace_packages.txt
src/Products.MeetingCPASLalouviere.egg-info/not-zip-safe
src/Products.MeetingCPASLalouviere.egg-info/requires.txt
src/Products.MeetingCPASLalouviere.egg-info/top_level.txt
src/Products/MeetingCPASLalouviere/README.txt
src/Products/MeetingCPASLalouviere/__init__.py
src/Products/MeetingCPASLalouviere/adapters.py
src/Products/MeetingCPASLalouviere/config.py
src/Products/MeetingCPASLalouviere/configure.zcml
src/Products/MeetingCPASLalouviere/events.py
src/Products/MeetingCPASLalouviere/interfaces.py
src/Products/MeetingCPASLalouviere/overrides.zcml
src/Products/MeetingCPASLalouviere/profiles.zcml
src/Products/MeetingCPASLalouviere/refresh.txt
src/Products/MeetingCPASLalouviere/setuphandlers.py
src/Products/MeetingCPASLalouviere/testing.py
src/Products/MeetingCPASLalouviere/testing.zcml
src/Products/MeetingCPASLalouviere/browser/__init__.py
src/Products/MeetingCPASLalouviere/browser/configure.zcml
src/Products/MeetingCPASLalouviere/locales/PloneMeeting.pot
src/Products/MeetingCPASLalouviere/locales/plone.pot
src/Products/MeetingCPASLalouviere/locales/sync_pos.sh
src/Products/MeetingCPASLalouviere/locales/en/LC_MESSAGES/PloneMeeting.po
src/Products/MeetingCPASLalouviere/locales/en/LC_MESSAGES/plone.po
src/Products/MeetingCPASLalouviere/locales/fr/LC_MESSAGES/PloneMeeting.po
src/Products/MeetingCPASLalouviere/locales/fr/LC_MESSAGES/plone.po
src/Products/MeetingCPASLalouviere/migrations/__init__.py
src/Products/MeetingCPASLalouviere/migrations/migrate_to_4200.py
src/Products/MeetingCPASLalouviere/profiles/__init__.py
src/Products/MeetingCPASLalouviere/profiles/default/MeetingCPASLalouviere_marker.txt
src/Products/MeetingCPASLalouviere/profiles/default/__init__.py
src/Products/MeetingCPASLalouviere/profiles/default/cssregistry.xml
src/Products/MeetingCPASLalouviere/profiles/default/import_steps.xml
src/Products/MeetingCPASLalouviere/profiles/default/jsregistry.xml
src/Products/MeetingCPASLalouviere/profiles/default/metadata.xml
